casbin_async_redis_watcher/__init__.py
casbin_async_redis_watcher/options.py
casbin_async_redis_watcher/watcher.py
casbin_async_redis_watcher-0.0.1.dist-info/LICENSE
casbin_async_redis_watcher-0.0.1.dist-info/METADATA
casbin_async_redis_watcher-0.0.1.dist-info/WHEEL
casbin_async_redis_watcher-0.0.1.dist-info/top_level.txt
casbin_async_redis_watcher-0.0.1.dist-info/RECORD
