Metadata-Version: 2.1
Name: casbin-async-redis-watcher
Version: 0.0.1
Summary: Async Casbin role watcher to be used for monitoring updates to policies for PyCasbin
Home-page: https://github.com/kevinkelin/casbin_async_redis_watcher
Author: yangyanxing
Author-email: yanxingyang@gmail.com
Classifier: Programming Language :: Python :: 3.6
Classifier: Programming Language :: Python :: 3.7
Classifier: Programming Language :: Python :: 3.8
Classifier: Programming Language :: Python :: 3.9
Classifier: Programming Language :: Python :: 3.10
Classifier: License :: OSI Approved :: Apache Software License
Requires-Python: >=3.6
License-File: LICENSE
Requires-Dist: redis >=4.2.0rc1
Requires-Dist: casbin >=1.18
